src/__init__.py
src/lib.py
src/main.py
fortune_cookie_demo-0.0.5.dist-info/METADATA
fortune_cookie_demo-0.0.5.dist-info/WHEEL
fortune_cookie_demo-0.0.5.dist-info/entry_points.txt
fortune_cookie_demo-0.0.5.dist-info/top_level.txt
fortune_cookie_demo-0.0.5.dist-info/RECORD
