Metadata-Version: 2.1
Name: fortune-cookie-demo
Version: 0.0.5
Summary: demo python CLI tool to generate random fortunes
Home-page: https://github.com/nogibjj/week7_afraa_simrun_fortune_cookie
Author: Simrun & Afraa
License: UNKNOWN
Platform: UNKNOWN
Requires-Dist: wheel (==0.37.1)
Requires-Dist: black (==22.3.0)
Requires-Dist: pytest (==7.1.3)
Requires-Dist: pytest-cov (==4.0.0)
Requires-Dist: pylint (==2.15.3)
Requires-Dist: boto3 (==1.24.87)
Requires-Dist: jupyter (==1.0.0)
Requires-Dist: pandas (==1.5.0)
Requires-Dist: fire
Requires-Dist: click
Requires-Dist: emoji
